riddles_solver/__init__.py
riddles_solver/async_client.py
riddles_solver/cli.py
riddles_solver/client.py
riddles_solver/key_extractor.py
riddles_solver-1.0.0.dist-info/LICENSE
riddles_solver-1.0.0.dist-info/METADATA
riddles_solver-1.0.0.dist-info/WHEEL
riddles_solver-1.0.0.dist-info/entry_points.txt
riddles_solver-1.0.0.dist-info/top_level.txt
riddles_solver-1.0.0.dist-info/RECORD
